nlp_dataset_engine/__init__.py
nlp_dataset_engine/benchmark.py
nlp_dataset_engine/checkpoint.py
nlp_dataset_engine/cli.py
nlp_dataset_engine/compression.py
nlp_dataset_engine/crawler.py
nlp_dataset_engine/hashing.py
nlp_dataset_engine/jsonl_writer.py
nlp_dataset_engine/loader.py
nlp_dataset_engine/manifest.py
nlp_dataset_engine/sharder.py
nlp_dataset_engine/stats.py
nlp_dataset_engine/streamer.py
nlp_dataset_engine/validators.py
nlp_engine_yuvraj-0.1.1.dist-info/METADATA
nlp_engine_yuvraj-0.1.1.dist-info/WHEEL
nlp_engine_yuvraj-0.1.1.dist-info/entry_points.txt
nlp_engine_yuvraj-0.1.1.dist-info/top_level.txt
nlp_engine_yuvraj-0.1.1.dist-info/RECORD
