Metadata-Version: 2.4
Name: nlp-engine-yuvraj
Version: 0.1.1
Summary: High-performance streaming NLP dataset ingestion engine
Author: Yuvraj
License: MIT
Requires-Python: >=3.8
Requires-Dist: tqdm>=4.0.0
Requires-Dist: langdetect>=1.0.9
Provides-Extra: dev
Requires-Dist: pytest>=7.0; extra == "dev"
Requires-Dist: black; extra == "dev"
Requires-Dist: flake8; extra == "dev"
